{
 "action": "Create Entry",
 "action_label": "Create Academic Terms",
 "creation": "2025-11-28 10:05:03.483222",
 "description": "Start/end dates that drive every deadline downstream",
 "docstatus": 0,
 "doctype": "Onboarding Step",
 "idx": 0,
 "is_complete": 0,
 "is_single": 0,
 "is_skipped": 0,
 "modified": "2026-04-29 14:35:00.736327",
 "modified_by": "Administrator",
 "name": "Academic Terms",
 "owner": "Administrator",
 "path": "",
 "reference_document": "Academic Term",
 "show_form_tour": 0,
 "show_full_form": 0,
 "title": "Create Academic Terms",
 "validate_action": 1
}
