{
 "actions": [],
 "creation": "2026-06-18 00:00:00.000000",
 "doctype": "DocType",
 "editable_grid": 1,
 "engine": "InnoDB",
 "field_order": [
  "kind",
  "course",
  "graduation_requirement_item",
  "gating_assessment",
  "exempt_if_score_at_least",
  "note"
 ],
 "fields": [
  {
   "columns": 2,
   "fieldname": "kind",
   "fieldtype": "Select",
   "in_list_view": 1,
   "label": "Kind",
   "options": "Leveling Course\nCourse Exemption\nPlacement Assessment\nRequirement Waiver",
   "reqd": 1
  },
  {
   "columns": 2,
   "depends_on": "eval:['Leveling Course','Course Exemption'].includes(doc.kind)",
   "fieldname": "course",
   "fieldtype": "Link",
   "in_list_view": 1,
   "label": "Course",
   "options": "Course"
  },
  {
   "columns": 2,
   "depends_on": "eval:doc.kind=='Requirement Waiver'",
   "description": "The graduation requirement to waive (advanced standing).",
   "fieldname": "graduation_requirement_item",
   "fieldtype": "Link",
   "in_list_view": 1,
   "label": "Graduation Requirement",
   "options": "Graduation Requirement Item"
  },
  {
   "columns": 2,
   "depends_on": "eval:['Leveling Course','Placement Assessment'].includes(doc.kind)",
   "description": "On a Placement Assessment row: the exam itself. On a Leveling Course row: the placement exam whose score gates this course (leave blank for an unconditionally-required leveling course).",
   "fieldname": "gating_assessment",
   "fieldtype": "Link",
   "in_list_view": 1,
   "label": "Placement Assessment",
   "options": "Placement Assessment"
  },
  {
   "columns": 1,
   "depends_on": "eval:doc.kind=='Leveling Course'",
   "description": "At or above this Placement Assessment score the course is placed out (Exempt) instead of required. Used only when a Placement Assessment gates this course.",
   "fieldname": "exempt_if_score_at_least",
   "fieldtype": "Float",
   "in_list_view": 1,
   "label": "Exempt if Score ≥",
   "non_negative": 1,
   "precision": "2"
  },
  {
   "fieldname": "note",
   "fieldtype": "Small Text",
   "label": "Note"
  }
 ],
 "istable": 1,
 "links": [],
 "modified": "2026-06-18 00:00:00.000000",
 "modified_by": "Administrator",
 "module": "Seminary",
 "name": "Leveling Profile Item",
 "owner": "Administrator",
 "permissions": [],
 "row_format": "Dynamic",
 "sort_field": "creation",
 "sort_order": "DESC",
 "states": []
}
