{
 "actions": [],
 "allow_rename": 1,
 "autoname": "field:category",
 "creation": "2016-09-05 06:28:33.679415",
 "doctype": "DocType",
 "editable_grid": 1,
 "engine": "InnoDB",
 "field_order": [
  "category"
 ],
 "fields": [
  {
   "fieldname": "category",
   "fieldtype": "Data",
   "in_list_view": 1,
   "label": "Category",
   "reqd": 1,
   "unique": 1
  }
 ],
 "istable": 1,
 "links": [
  {
   "group": "Fee",
   "link_doctype": "Fee Structure",
   "link_fieldname": "student_category"
  },
  {
   "group": "Fee",
   "link_doctype": "Fee Schedule",
   "link_fieldname": "student_category"
  }
 ],
 "modified": "2024-03-04 23:59:50.787458",
 "modified_by": "Administrator",
 "module": "Seminary",
 "name": "Student Category",
 "naming_rule": "By fieldname",
 "owner": "Administrator",
 "permissions": [],
 "quick_entry": 1,
 "sort_field": "modified",
 "sort_order": "DESC",
 "states": []
}